qfaas/__init__.py
qfaas/backend.py
qfaas/dataUtils.py
qfaas/utilities.py
qfaas/algorithms/__init__.py
qfaas/algorithms/shor.py
qfaas/sdk/__init__.py
qfaas/sdk/braket.py
qfaas/sdk/cirq.py
qfaas/sdk/qiskit.py
qfaas/sdk/qsharp.py
qfaas-0.2.3.dist-info/LICENSE
qfaas-0.2.3.dist-info/METADATA
qfaas-0.2.3.dist-info/WHEEL
qfaas-0.2.3.dist-info/top_level.txt
qfaas-0.2.3.dist-info/RECORD
