Metadata-Version: 2.1
Name: qfaas
Version: 0.2.3
Summary: QFaaS Library supporting QFaaS Serverless framework for Quantum Computing
Author-email: Hoa Nguyen <hoa@hoaio.com>
License: The MIT License (MIT)
Project-URL: Homepage, https://quantumai.cloud
Keywords: qfaas,quantum,serverless
Classifier: License :: OSI Approved :: MIT License
Classifier: Programming Language :: Python
Classifier: Programming Language :: Python :: 3
Requires-Python: >=3.7
License-File: LICENSE
Requires-Dist: qiskit (==0.36.1)
Requires-Dist: cirq (==1.0.0)
Requires-Dist: amazon-braket-sdk (==1.19.0)
Requires-Dist: numpy (>=1.22.3)
Requires-Dist: strangeworks (==0.2.13)
Requires-Dist: strangeworks-braket (==0.1.3)
Provides-Extra: dev
Requires-Dist: black ; extra == 'dev'
Requires-Dist: bumpver ; extra == 'dev'
Requires-Dist: isort ; extra == 'dev'
Requires-Dist: pip-tools ; extra == 'dev'
Requires-Dist: pytest ; extra == 'dev'
